setup.py
imputing_final/__init__.py
imputing_final/imputing_final.py
imputing_final.egg-info/PKG-INFO
imputing_final.egg-info/SOURCES.txt
imputing_final.egg-info/dependency_links.txt
imputing_final.egg-info/requires.txt
imputing_final.egg-info/top_level.txt